Metadata-Version: 2.1
Name: webfscholar
Version: 0.0.3
Summary: Generate publications webpages from Google Scholar
Home-page: https://github.com/alvinwan/webfscholar
Author: Alvin Wan
Author-email: hi@alvinwan.com
License: UNKNOWN
Download-URL: https://github.com/alvinwan/webfscholar/archive/0.0.3.zip
Platform: UNKNOWN
Classifier: Intended Audience :: Developers
Classifier: Programming Language :: Python :: 3
Classifier: License :: OSI Approved :: MIT License
Classifier: Operating System :: OS Independent
Requires-Python: >=3.5
